odoo/addons/stock_inventory_quantity_history/README.rst
odoo/addons/stock_inventory_quantity_history/__init__.py
odoo/addons/stock_inventory_quantity_history/__manifest__.py
odoo/addons/stock_inventory_quantity_history/i18n/it.po
odoo/addons/stock_inventory_quantity_history/i18n/stock_inventory_quantity_history.pot
odoo/addons/stock_inventory_quantity_history/models/__init__.py
odoo/addons/stock_inventory_quantity_history/models/stock_move_line.py
odoo/addons/stock_inventory_quantity_history/models/stock_quant.py
odoo/addons/stock_inventory_quantity_history/readme/CONTRIBUTORS.rst
odoo/addons/stock_inventory_quantity_history/readme/DESCRIPTION.rst
odoo/addons/stock_inventory_quantity_history/readme/USAGE.rst
odoo/addons/stock_inventory_quantity_history/static/description/icon.png
odoo/addons/stock_inventory_quantity_history/static/description/index.html
odoo/addons/stock_inventory_quantity_history/tests/__init__.py
odoo/addons/stock_inventory_quantity_history/tests/test_inventory_quantity_history.py
odoo/addons/stock_inventory_quantity_history/views/stock_move_line_views.xml
odoo_addon_stock_inventory_quantity_history-16.0.1.0.0.4.dist-info/METADATA
odoo_addon_stock_inventory_quantity_history-16.0.1.0.0.4.dist-info/WHEEL
odoo_addon_stock_inventory_quantity_history-16.0.1.0.0.4.dist-info/top_level.txt
odoo_addon_stock_inventory_quantity_history-16.0.1.0.0.4.dist-info/RECORD
